pumaguard/__init__.py
pumaguard/classify.py
pumaguard/lock_manager.py
pumaguard/main.py
pumaguard/model-registry.yaml
pumaguard/model_cli.py
pumaguard/model_downloader.py
pumaguard/presets.py
pumaguard/server.py
pumaguard/sound.py
pumaguard/stats.py
pumaguard/utils.py
pumaguard/verify.py
pumaguard/web_ui.py
pumaguard/completions/pumaguard-classify-completions.sh
pumaguard/completions/pumaguard-completions.sh
pumaguard/completions/pumaguard-server-completions.sh
pumaguard/completions/pumaguard-train-completions.sh
pumaguard/pumaguard-ui/.last_build_id
pumaguard/pumaguard-ui/favicon.png
pumaguard/pumaguard-ui/flutter.js
pumaguard/pumaguard-ui/flutter_bootstrap.js
pumaguard/pumaguard-ui/flutter_service_worker.js
pumaguard/pumaguard-ui/index.html
pumaguard/pumaguard-ui/main.dart.js
pumaguard/pumaguard-ui/manifest.json
pumaguard/pumaguard-ui/version.json
pumaguard/pumaguard-ui/assets/AssetManifest.bin
pumaguard/pumaguard-ui/assets/AssetManifest.bin.json
pumaguard/pumaguard-ui/assets/FontManifest.json
pumaguard/pumaguard-ui/assets/NOTICES
pumaguard/pumaguard-ui/assets/fonts/MaterialIcons-Regular.otf
pumaguard/pumaguard-ui/assets/fonts/Roboto-Bold.ttf
pumaguard/pumaguard-ui/assets/fonts/Roboto-Light.ttf
pumaguard/pumaguard-ui/assets/fonts/Roboto-Medium.ttf
pumaguard/pumaguard-ui/assets/fonts/Roboto-Regular.ttf
pumaguard/pumaguard-ui/assets/fonts/RobotoMono-Bold.ttf
pumaguard/pumaguard-ui/assets/fonts/RobotoMono-Medium.ttf
pumaguard/pumaguard-ui/assets/fonts/RobotoMono-Regular.ttf
pumaguard/pumaguard-ui/assets/packages/cupertino_icons/assets/CupertinoIcons.ttf
pumaguard/pumaguard-ui/assets/shaders/ink_sparkle.frag
pumaguard/pumaguard-ui/assets/shaders/stretch_effect.frag
pumaguard/pumaguard-ui/canvaskit/canvaskit.js
pumaguard/pumaguard-ui/canvaskit/canvaskit.js.symbols
pumaguard/pumaguard-ui/canvaskit/canvaskit.wasm
pumaguard/pumaguard-ui/canvaskit/skwasm.js
pumaguard/pumaguard-ui/canvaskit/skwasm.js.symbols
pumaguard/pumaguard-ui/canvaskit/skwasm.wasm
pumaguard-20.post250.dist-info/licenses/LICENSE
pumaguard-20.post250.dist-info/METADATA
pumaguard-20.post250.dist-info/WHEEL
pumaguard-20.post250.dist-info/entry_points.txt
pumaguard-20.post250.dist-info/top_level.txt
pumaguard-20.post250.dist-info/RECORD
