Metadata-Version: 2.4
Name: pumaguard
Version: 20.post250
Author-email: Nicolas Bock <nicolasbock@gmail.com>
Project-URL: Homepage, http://pumaguard.rtfd.io/
Project-URL: Repository, https://github.com/PEEC-Nature-Youth-Group/pumaguard
Requires-Python: <4.0,>=3.10
License-File: LICENSE
Requires-Dist: flask~=3.1
Requires-Dist: flask-cors~=6.0
Requires-Dist: matplotlib~=3.10
Requires-Dist: packaging~=25.0
Requires-Dist: pillow~=11.1
Requires-Dist: pyyaml~=6.0
Requires-Dist: tensorflow-cpu<2.21,>=2.18; platform_machine != "aarch64" and platform_machine != "arm64"
Requires-Dist: tensorflow<2.21,>=2.18; platform_machine == "aarch64" or platform_machine == "arm64"
Requires-Dist: tf-keras<2.21,>=2.18
Requires-Dist: torch~=2.9
Requires-Dist: ultralytics~=8.3
Requires-Dist: requests~=2.32
Requires-Dist: zeroconf~=0.136
Provides-Extra: dev
Requires-Dist: ansible-lint~=25.2; platform_system != "Windows" and extra == "dev"
Requires-Dist: ansible~=10.7; extra == "dev"
Requires-Dist: bashate~=2.1; extra == "dev"
Requires-Dist: black~=25.9; extra == "dev"
Requires-Dist: build~=1.3; extra == "dev"
Requires-Dist: esbonio~=1.0; extra == "dev"
Requires-Dist: isort~=6.0; extra == "dev"
Requires-Dist: mypy~=1.18; extra == "dev"
Requires-Dist: passlib~=1.7; extra == "dev"
Requires-Dist: pip~=24.3; extra == "dev"
Requires-Dist: pylint~=3.3; extra == "dev"
Requires-Dist: pytest-cov~=7.0; extra == "dev"
Requires-Dist: pytest~=8.3; extra == "dev"
Provides-Extra: extra-dev
Requires-Dist: ipykernel~=6.29; extra == "extra-dev"
Requires-Dist: plotly~=6.0; extra == "extra-dev"
Provides-Extra: docs
Requires-Dist: cloud-sptheme; extra == "docs"
Requires-Dist: matplotlib~=3.10; extra == "docs"
Requires-Dist: pandas~=2.3; extra == "docs"
Requires-Dist: pillow~=11.1; extra == "docs"
Requires-Dist: playsound3; extra == "docs"
Requires-Dist: sphinx-book-theme; extra == "docs"
Requires-Dist: sphinx-copybutton; extra == "docs"
Requires-Dist: sphinx-new-tab-link; extra == "docs"
Requires-Dist: sphinxcontrib-mermaid; extra == "docs"
Requires-Dist: tensorflow<2.21,>=2.18; extra == "docs"
Requires-Dist: ultralytics~=8.3; extra == "docs"
Dynamic: license-file
